roboflex/dynamixel/__init__.py
roboflex/dynamixel/roboflex_dynamixel_ext.cpython-311-darwin.so
roboflex_dynamixel-0.1.20.dist-info/licenses/LICENSE
roboflex_dynamixel-0.1.20.dist-info/METADATA
roboflex_dynamixel-0.1.20.dist-info/WHEEL
roboflex_dynamixel-0.1.20.dist-info/top_level.txt
roboflex_dynamixel-0.1.20.dist-info/RECORD
