Metadata-Version: 2.4
Name: roboflex.dynamixel
Version: 0.1.20
Summary: Roboflex Dynamixel Library
Home-page: https://github.com/flexrobotics/roboflex_dynamixel
Author: Colin Prepscius
Author-email: colinprepscius@gmail.com
License: MIT
Keywords: dynamixel,robotics,middleware,flexbuffers,python,c++,c++20
Classifier: Intended Audience :: Developers
Classifier: License :: OSI Approved :: MIT License
Classifier: Topic :: Software Development :: Libraries :: Python Modules
Classifier: Topic :: Software Development :: Embedded Systems
Classifier: Framework :: Robot Framework
Classifier: Framework :: Robot Framework :: Library
Classifier: Framework :: Robot Framework :: Tool
Classifier: Programming Language :: C++
Classifier: Programming Language :: Python :: 3
Requires-Python: >=3.6
License-File: LICENSE
Requires-Dist: numpy
Requires-Dist: roboflex
Dynamic: author
Dynamic: author-email
Dynamic: classifier
Dynamic: description
Dynamic: description-content-type
Dynamic: home-page
Dynamic: keywords
Dynamic: license
Dynamic: license-file
Dynamic: requires-dist
Dynamic: requires-python
Dynamic: summary
